Metadata-Version: 2.1
Name: rdflib-jsonld
Version: 0.6.1
Summary: rdflib extension adding JSON-LD parser and serializer
Home-page: https://github.com/RDFLib/rdflib-jsonld
Maintainer: RDFLib Team
Maintainer-email: rdflib-dev@google.com
License: BSD
Platform: any
Classifier: Programming Language :: Python
Classifier: Programming Language :: Python :: 3
Classifier: Programming Language :: Python :: 3.6
Classifier: Programming Language :: Python :: 3.7
Classifier: Programming Language :: Python :: 3.8
Classifier: Programming Language :: Python :: 3.9
Classifier: License :: OSI Approved :: BSD License
Classifier: Topic :: Software Development :: Libraries :: Python Modules
Classifier: Operating System :: OS Independent
Classifier: Natural Language :: English
License-File: LICENSE.md
